cpen/__init__.py
cpen/codepen_downloader.py
cpen/templates/__init__.py
cpen/templates/index.html
cpen-0.1.2.dist-info/LICENSE.md
cpen-0.1.2.dist-info/METADATA
cpen-0.1.2.dist-info/WHEEL
cpen-0.1.2.dist-info/entry_points.txt
cpen-0.1.2.dist-info/top_level.txt
cpen-0.1.2.dist-info/RECORD
